<?xml version="1.0" encoding="UTF-8"?>
<?OFX OFXHEADER="200" VERSION="202" SECURITY="NONE" OLDFILEUID="NONE" NEWFILEUID="NONE" ?>
<OFX>
  <TAX1099MSGSRSV1>
    <TAX1099TRNRS>
      <TRNUID>f324cca1-ffc1-4ef3-8495-b272f5cb2e7d</TRNUID>
      <STATUS>
        <CODE>0</CODE>
        <SEVERITY>INFO</SEVERITY>
        <MESSAGE>SUCCESS</MESSAGE>
      </STATUS>
      <TAX1099RS>
        <FIDIRECTDEPOSITINFO>
          <FINAME_DIRECTDEPOSIT>Charles Schwab &amp; Co., Inc.</FINAME_DIRECTDEPOSIT>
          <FIROUTINGNUM>071000013</FIROUTINGNUM>
          <FIACCTNUM>59385380077373781</FIACCTNUM>
        </FIDIRECTDEPOSITINFO>
        <TAX1099DIV_V100>
          <SRVRTID>103089</SRVRTID>
          <TAXYEAR>2024</TAXYEAR>
          <CORRECTED>N</CORRECTED>
          <ORDDIV>1607.03</ORDDIV>
          <QUALIFIEDDIV>39.84</QUALIFIEDDIV>
          <SEC199A>1.69</SEC199A>
          <EXEMPTINTDIV>0.00</EXEMPTINTDIV>
          <SPECIFIEDPABINTDIV>0.00</SPECIFIEDPABINTDIV>
          <PAYERADDR>
            <PAYERNAME1>CHARLES SCHWAB &amp; CO., INC.</PAYERNAME1>
            <ADDR1>211 MAIN ST.</ADDR1>
            <CITY>SAN FRANCISCO</CITY>
            <STATE>CA</STATE>
            <POSTALCODE>94105</POSTALCODE>
          </PAYERADDR>
          <PAYERID>94-1737782</PAYERID>
          <RECID>XXXXX0238</RECID>
          <RECACCT>77373781</RECACCT>
        </TAX1099DIV_V100>
        <TAX1099INT_V100>
          <SRVRTID>103090</SRVRTID>
          <TAXYEAR>2024</TAXYEAR>
          <CORRECTED>N</CORRECTED>
          <INTINCOME>6.19</INTINCOME>
          <BONDPREMUSOBLIGATIONS>0.00</BONDPREMUSOBLIGATIONS>
          <PAYERADDR>
            <PAYERNAME1>CHARLES SCHWAB &amp; CO., INC.</PAYERNAME1>
            <ADDR1>211 MAIN ST.</ADDR1>
            <CITY>SAN FRANCISCO</CITY>
            <STATE>CA</STATE>
            <POSTALCODE>94105</POSTALCODE>
          </PAYERADDR>
          <PAYERID>94-1737782</PAYERID>
          <RECID>XXXXX0238</RECID>
          <RECACCT>77373781</RECACCT>
          <FATCA>N</FATCA>
        </TAX1099INT_V100>
      </TAX1099RS>
    </TAX1099TRNRS>
  </TAX1099MSGSRSV1>
</OFX>